MANIFEST.in
README.rst
setup.py
collective/__init__.py
collective.liches.egg-info/PKG-INFO
collective.liches.egg-info/SOURCES.txt
collective.liches.egg-info/dependency_links.txt
collective.liches.egg-info/entry_points.txt
collective.liches.egg-info/namespace_packages.txt
collective.liches.egg-info/not-zip-safe
collective.liches.egg-info/paster_plugins.txt
collective.liches.egg-info/requires.txt
collective.liches.egg-info/top_level.txt
collective/liches/README.txt
collective/liches/__init__.py
collective/liches/configure.zcml
collective/liches/interfaces.py
collective/liches/setuphandlers.py
collective/liches/tests.py
collective/liches/browser/__init__.py
collective/liches/browser/brokenlinks.pt
collective/liches/browser/brokenpages.pt
collective/liches/browser/configure.zcml
collective/liches/browser/lichesviewlet.pt
collective/liches/browser/settings.py
collective/liches/browser/startp.pt
collective/liches/browser/viewlets.py
collective/liches/browser/views.py
collective/liches/browser/static/liches.css
collective/liches/portlets/__init__.py
collective/liches/portlets/ajaxview.pt
collective/liches/portlets/configure.zcml
collective/liches/portlets/lichesportlet.pt
collective/liches/portlets/lichesportlet.py
collective/liches/portlets/views.py
collective/liches/profiles/default/browserlayer.xml
collective/liches/profiles/default/controlpanel.xml
collective/liches/profiles/default/cssregistry.xml
collective/liches/profiles/default/metadata.xml
collective/liches/profiles/default/portlets.xml
collective/liches/profiles/default/registry.xml
collective/liches/tests/__init__.py
collective/liches/tests/base_lichesportlet.py
collective/liches/tests/test_lichesportlet.py
docs/HISTORY.txt
docs/INSTALL.txt
docs/LICENSE.GPL
docs/LICENSE.txt