Metadata-Version: 1.0
Name: collective.liches
Version: 0.2
Summary: Integrate linkchecker into plone
Home-page: https://github.com/collective/collective.liches
Author: Christian Ledermann
Author-email: christian.ledermann@gmail.com
License: GPL
Platform: UNKNOWN
Classifier: Framework :: Plone
Classifier: Programming Language :: Python
Classifier: Topic :: Internet :: WWW/HTTP :: Site Management :: Link Checking
Classifier: Framework :: Plone :: 4.2
Classifier: Framework :: Plone :: 4.1
Classifier: License :: OSI Approved :: GNU General Public License v2 (GPLv2)
